euc/base/__init__.py
euc/cli/__init__.py
euc/cli/__main__.py
euc/device/__init__.py
euc/utils/__init__.py
euc-0.2.0.dist-info/LICENSE
euc-0.2.0.dist-info/METADATA
euc-0.2.0.dist-info/WHEEL
euc-0.2.0.dist-info/top_level.txt
euc-0.2.0.dist-info/zip-safe
euc-0.2.0.dist-info/RECORD
